scan2folder/__init__.py
scan2folder/__main__.py
scan2folder/configform.ui
scan2folder/dialog.ui
scan2folder/imagecalibrate.py
scan2folder/images/scan_bw.svg
scan2folder/images/scan_color.svg
scan2folder/images/scan_grey.svg
scan2folder/images/square_green.svg
scan2folder/images/square_red.svg
scan2folder/mainwindow.ui
scan2folder/multithread.py
scan2folder/ocrtools.py
scan2folder/pagesizes.json
scan2folder/resources.py
scan2folder/resources.qrc
scan2folder/rubberband.py
scan2folder/scan2folder.py
scan2folder/ui_configform.py
scan2folder/ui_dialog.py
scan2folder-0.2.3.dist-info/WHEEL
scan2folder-0.2.3.dist-info/METADATA
scan2folder-0.2.3.dist-info/RECORD
