Metadata-Version: 2.3
Name: scan2folder
Version: 0.2.3
Summary: Scan tool for HP MF Printers
Keywords: scan button,scan tool,HP MFP,sane
Author: Alfredo Cubitos
Requires-Dist: pyqt6
Requires-Dist: python-sane
Requires-Dist: bs4
Requires-Dist: lxml
Requires-Dist: pillow
Requires-Dist: wand
Requires-Dist: pytesseract
Requires-Dist: numpy
Requires-Python: >=3.13
Project-URL: Homepage, https://github.com/AlfredoCubitos/Scan2Folder
